README.md
pyproject.toml
setup.py
metrics_exporter/MetricsExporter.py
metrics_exporter/__init__.py
metrics_exporter/__main__.py
metrics_exporter.egg-info/PKG-INFO
metrics_exporter.egg-info/SOURCES.txt
metrics_exporter.egg-info/dependency_links.txt
metrics_exporter.egg-info/top_level.txt